{
  "version": "2.5.0",
  "summary": {
    "title": "New Threat Model",
    "owner": "",
    "description": "",
    "id": 0
  },
  "detail": {
    "contributors": [],
    "diagrams": [
      {
        "id": 0,
        "title": "New STRIDE diagram",
        "diagramType": "STRIDE",
        "placeholder": "New STRIDE diagram description",
        "thumbnail": "./public/content/images/thumbnail.stride.jpg",
        "version": "2.5.0",
        "cells": [
          {
            "position": {
              "x": 370,
              "y": 100
            },
            "size": {
              "width": 60,
              "height": 60
            },
            "attrs": {
              "text": {
                "text": "Elevation Of\nPrivilege"
              },
              "body": {
                "stroke": "#333333",
                "strokeWidth": 1.5,
                "strokeDasharray": null
              }
            },
            "visible": true,
            "shape": "process",
            "ports": {
              "groups": {
                "top": {
                  "position": "top",
                  "attrs": {
                    "circle": {
                      "r": 4,
                      "magnet": true,
                      "stroke": "#5F95FF",
                      "strokeWidth": 1,
                      "fill": "#fff",
                      "style": {
                        "visibility": "hidden"
                      }
                    }
                  }
                },
                "right": {
                  "position": "right",
                  "attrs": {
                    "circle": {
                      "r": 4,
                      "magnet": true,
                      "stroke": "#5F95FF",
                      "strokeWidth": 1,
                      "fill": "#fff",
                      "style": {
                        "visibility": "hidden"
                      }
                    }
                  }
                },
                "bottom": {
                  "position": "bottom",
                  "attrs": {
                    "circle": {
                      "r": 4,
                      "magnet": true,
                      "stroke": "#5F95FF",
                      "strokeWidth": 1,
                      "fill": "#fff",
                      "style": {
                        "visibility": "hidden"
                      }
                    }
                  }
                },
                "left": {
                  "position": "left",
                  "attrs": {
                    "circle": {
                      "r": 4,
                      "magnet": true,
                      "stroke": "#5F95FF",
                      "strokeWidth": 1,
                      "fill": "#fff",
                      "style": {
                        "visibility": "hidden"
                      }
                    }
                  }
                }
              },
              "items": [
                {
                  "group": "top",
                  "id": "3eb5b585-f462-4f52-939f-818d15bb5ada"
                },
                {
                  "group": "right",
                  "id": "a588080b-c81e-4b55-8afe-fca5e46af7aa"
                },
                {
                  "group": "bottom",
                  "id": "4f796765-502e-4078-bee6-8dc96b106a0b"
                },
                {
                  "group": "left",
                  "id": "aa0c7dcd-3ec4-44ff-b7db-4326be7086be"
                }
              ]
            },
            "id": "525358c0-9263-4a25-82f9-9df919167926",
            "zIndex": 1,
            "data": {
              "type": "tm.Process",
              "name": "Elevation Of\nPrivilege",
              "description": "",
              "outOfScope": false,
              "isTrustBoundary": false,
              "reasonOutOfScope": "",
              "hasOpenThreats": false,
              "handlesCardPayment": false,
              "handlesGoodsOrServices": false,
              "isWebApplication": false,
              "privilegeLevel": "",
              "threats": []
            }
          },
          {
            "position": {
              "x": 751,
              "y": 100
            },
            "size": {
              "width": 60,
              "height": 60
            },
            "attrs": {
              "body": {
                "stroke": "#333333",
                "strokeWidth": 1.5,
                "strokeDasharray": null
              }
            },
            "visible": true,
            "shape": "process",
            "ports": {
              "groups": {
                "top": {
                  "position": "top",
                  "attrs": {
                    "circle": {
                      "r": 4,
                      "magnet": true,
                      "stroke": "#5F95FF",
                      "strokeWidth": 1,
                      "fill": "#fff",
                      "style": {
                        "visibility": "hidden"
                      }
                    }
                  }
                },
                "right": {
                  "position": "right",
                  "attrs": {
                    "circle": {
                      "r": 4,
                      "magnet": true,
                      "stroke": "#5F95FF",
                      "strokeWidth": 1,
                      "fill": "#fff",
                      "style": {
                        "visibility": "hidden"
                      }
                    }
                  }
                },
                "bottom": {
                  "position": "bottom",
                  "attrs": {
                    "circle": {
                      "r": 4,
                      "magnet": true,
                      "stroke": "#5F95FF",
                      "strokeWidth": 1,
                      "fill": "#fff",
                      "style": {
                        "visibility": "hidden"
                      }
                    }
                  }
                },
                "left": {
                  "position": "left",
                  "attrs": {
                    "circle": {
                      "r": 4,
                      "magnet": true,
                      "stroke": "#5F95FF",
                      "strokeWidth": 1,
                      "fill": "#fff",
                      "style": {
                        "visibility": "hidden"
                      }
                    }
                  }
                }
              },
              "items": [
                {
                  "group": "top",
                  "id": "3eb5b585-f462-4f52-939f-818d15bb5ada"
                },
                {
                  "group": "right",
                  "id": "a588080b-c81e-4b55-8afe-fca5e46af7aa"
                },
                {
                  "group": "bottom",
                  "id": "4f796765-502e-4078-bee6-8dc96b106a0b"
                },
                {
                  "group": "left",
                  "id": "aa0c7dcd-3ec4-44ff-b7db-4326be7086be"
                }
              ]
            },
            "id": "b896e27f-5fca-46d8-a86a-8916279dc7c9",
            "zIndex": 2,
            "data": {
              "type": "tm.Process",
              "name": "Process",
              "description": "",
              "outOfScope": false,
              "isTrustBoundary": false,
              "reasonOutOfScope": "",
              "hasOpenThreats": false,
              "handlesCardPayment": false,
              "handlesGoodsOrServices": false,
              "isWebApplication": false,
              "privilegeLevel": "",
              "threats": []
            }
          },
          {
            "position": {
              "x": 343.75,
              "y": 22
            },
            "size": {
              "width": 112.5,
              "height": 60
            },
            "attrs": {
              "text": {
                "text": "Authorization Provider\n"
              }
            },
            "visible": true,
            "shape": "td-text-block",
            "id": "af73098f-5073-43cc-b065-ae9cbe009b4d",
            "zIndex": 3,
            "data": {
              "type": "tm.Text",
              "name": "Authorization Provider\n",
              "hasOpenThreats": false
            }
          },
          {
            "position": {
              "x": 725,
              "y": 22
            },
            "size": {
              "width": 112.5,
              "height": 60
            },
            "attrs": {
              "text": {
                "text": "LDAP"
              }
            },
            "visible": true,
            "shape": "td-text-block",
            "id": "955ce204-0944-4379-932e-2f0a8b2c52cd",
            "zIndex": 4,
            "data": {
              "type": "tm.Text",
              "name": "LDAP",
              "hasOpenThreats": false
            }
          },
          {
            "position": {
              "x": 370,
              "y": 327
            },
            "size": {
              "width": 60,
              "height": 60
            },
            "attrs": {
              "body": {
                "stroke": "#333333",
                "strokeWidth": 1.5,
                "strokeDasharray": null
              }
            },
            "visible": true,
            "shape": "process",
            "ports": {
              "groups": {
                "top": {
                  "position": "top",
                  "attrs": {
                    "circle": {
                      "r": 4,
                      "magnet": true,
                      "stroke": "#5F95FF",
                      "strokeWidth": 1,
                      "fill": "#fff",
                      "style": {
                        "visibility": "hidden"
                      }
                    }
                  }
                },
                "right": {
                  "position": "right",
                  "attrs": {
                    "circle": {
                      "r": 4,
                      "magnet": true,
                      "stroke": "#5F95FF",
                      "strokeWidth": 1,
                      "fill": "#fff",
                      "style": {
                        "visibility": "hidden"
                      }
                    }
                  }
                },
                "bottom": {
                  "position": "bottom",
                  "attrs": {
                    "circle": {
                      "r": 4,
                      "magnet": true,
                      "stroke": "#5F95FF",
                      "strokeWidth": 1,
                      "fill": "#fff",
                      "style": {
                        "visibility": "hidden"
                      }
                    }
                  }
                },
                "left": {
                  "position": "left",
                  "attrs": {
                    "circle": {
                      "r": 4,
                      "magnet": true,
                      "stroke": "#5F95FF",
                      "strokeWidth": 1,
                      "fill": "#fff",
                      "style": {
                        "visibility": "hidden"
                      }
                    }
                  }
                }
              },
              "items": [
                {
                  "group": "top",
                  "id": "3eb5b585-f462-4f52-939f-818d15bb5ada"
                },
                {
                  "group": "right",
                  "id": "a588080b-c81e-4b55-8afe-fca5e46af7aa"
                },
                {
                  "group": "bottom",
                  "id": "4f796765-502e-4078-bee6-8dc96b106a0b"
                },
                {
                  "group": "left",
                  "id": "aa0c7dcd-3ec4-44ff-b7db-4326be7086be"
                }
              ]
            },
            "id": "edd5af30-973b-40be-b9c7-894a537276b1",
            "zIndex": 5,
            "data": {
              "type": "tm.Process",
              "name": "Process",
              "description": "",
              "outOfScope": false,
              "isTrustBoundary": false,
              "reasonOutOfScope": "",
              "hasOpenThreats": false,
              "handlesCardPayment": false,
              "handlesGoodsOrServices": false,
              "isWebApplication": false,
              "privilegeLevel": "",
              "threats": []
            }
          },
          {
            "position": {
              "x": 751,
              "y": 327
            },
            "size": {
              "width": 60,
              "height": 60
            },
            "attrs": {
              "body": {
                "stroke": "#333333",
                "strokeWidth": 1.5,
                "strokeDasharray": null
              }
            },
            "visible": true,
            "shape": "process",
            "ports": {
              "groups": {
                "top": {
                  "position": "top",
                  "attrs": {
                    "circle": {
                      "r": 4,
                      "magnet": true,
                      "stroke": "#5F95FF",
                      "strokeWidth": 1,
                      "fill": "#fff",
                      "style": {
                        "visibility": "hidden"
                      }
                    }
                  }
                },
                "right": {
                  "position": "right",
                  "attrs": {
                    "circle": {
                      "r": 4,
                      "magnet": true,
                      "stroke": "#5F95FF",
                      "strokeWidth": 1,
                      "fill": "#fff",
                      "style": {
                        "visibility": "hidden"
                      }
                    }
                  }
                },
                "bottom": {
                  "position": "bottom",
                  "attrs": {
                    "circle": {
                      "r": 4,
                      "magnet": true,
                      "stroke": "#5F95FF",
                      "strokeWidth": 1,
                      "fill": "#fff",
                      "style": {
                        "visibility": "hidden"
                      }
                    }
                  }
                },
                "left": {
                  "position": "left",
                  "attrs": {
                    "circle": {
                      "r": 4,
                      "magnet": true,
                      "stroke": "#5F95FF",
                      "strokeWidth": 1,
                      "fill": "#fff",
                      "style": {
                        "visibility": "hidden"
                      }
                    }
                  }
                }
              },
              "items": [
                {
                  "group": "top",
                  "id": "3eb5b585-f462-4f52-939f-818d15bb5ada"
                },
                {
                  "group": "right",
                  "id": "a588080b-c81e-4b55-8afe-fca5e46af7aa"
                },
                {
                  "group": "bottom",
                  "id": "4f796765-502e-4078-bee6-8dc96b106a0b"
                },
                {
                  "group": "left",
                  "id": "aa0c7dcd-3ec4-44ff-b7db-4326be7086be"
                }
              ]
            },
            "id": "eb824cc4-5667-4448-88ee-98e337f4da66",
            "zIndex": 6,
            "data": {
              "type": "tm.Process",
              "name": "Process",
              "description": "",
              "outOfScope": false,
              "isTrustBoundary": false,
              "reasonOutOfScope": "",
              "hasOpenThreats": false,
              "handlesCardPayment": false,
              "handlesGoodsOrServices": false,
              "isWebApplication": false,
              "privilegeLevel": "",
              "threats": []
            }
          },
          {
            "shape": "trust-boundary-curve",
            "width": 200,
            "height": 100,
            "zIndex": 10,
            "connector": "smooth",
            "data": {
              "type": "tm.Boundary",
              "name": "Trust Boundary",
              "description": "",
              "isTrustBoundary": true,
              "hasOpenThreats": false,
              "crossingFlows": [],
              "containedElements": []
            },
            "labels": [
              "Trust Boundary"
            ],
            "id": "79a2954f-ff10-4575-8d45-d47437bb25f7",
            "source": {
              "x": 670,
              "y": 70
            },
            "target": {
              "x": 670,
              "y": 460
            },
            "vertices": [
              {
                "x": 650,
                "y": 250
              }
            ]
          },
          {
            "shape": "trust-boundary-curve",
            "width": 200,
            "height": 100,
            "zIndex": 10,
            "connector": "smooth",
            "data": {
              "type": "tm.Boundary",
              "name": "Trust Boundary",
              "description": "",
              "isTrustBoundary": true,
              "hasOpenThreats": false,
              "crossingFlows": [],
              "containedElements": []
            },
            "labels": [
              "Trust Boundary"
            ],
            "id": "caacbfe0-d259-473f-92cb-097292752267",
            "source": {
              "x": 310,
              "y": 80
            },
            "target": {
              "x": 310,
              "y": 470
            },
            "vertices": [
              {
                "x": 280,
                "y": 270
              }
            ]
          },
          {
            "shape": "flow",
            "attrs": {
              "line": {
                "stroke": "#333333",
                "targetMarker": {
                  "name": "block"
                },
                "sourceMarker": {
                  "name": ""
                },
                "strokeDasharray": null
              }
            },
            "width": 200,
            "height": 100,
            "zIndex": 10,
            "connector": "smooth",
            "data": {
              "type": "tm.Flow",
              "name": "Insert Query with Feedback Comments",
              "description": "",
              "outOfScope": false,
              "isTrustBoundary": false,
              "reasonOutOfScope": "",
              "hasOpenThreats": false,
              "isBidirectional": false,
              "isEncrypted": false,
              "isPublicNetwork": false,
              "protocol": "",
              "threats": [],
              "trustBoundaryIds": []
            },
            "labels": [
              "Insert Query with Feedback Comments"
            ],
            "id": "e542180a-9880-4273-9f89-5a8c55574bc9",
            "source": {
              "cell": "edd5af30-973b-40be-b9c7-894a537276b1",
              "port": "a588080b-c81e-4b55-8afe-fca5e46af7aa"
            },
            "target": {
              "cell": "eb824cc4-5667-4448-88ee-98e337f4da66",
              "port": "aa0c7dcd-3ec4-44ff-b7db-4326be7086be"
            },
            "vertices": []
          },
          {
            "shape": "flow",
            "attrs": {
              "line": {
                "stroke": "#333333",
                "targetMarker": {
                  "name": "block"
                },
                "sourceMarker": {
                  "name": ""
                },
                "strokeDasharray": null
              }
            },
            "width": 200,
            "height": 100,
            "zIndex": 10,
            "connector": "smooth",
            "data": {
              "type": "tm.Flow",
              "name": "Success = 1",
              "description": "",
              "outOfScope": false,
              "isTrustBoundary": false,
              "reasonOutOfScope": "",
              "hasOpenThreats": false,
              "isBidirectional": false,
              "isEncrypted": false,
              "isPublicNetwork": false,
              "protocol": "",
              "threats": [],
              "trustBoundaryIds": []
            },
            "labels": [
              "Success = 1"
            ],
            "id": "18c4f59d-ff18-4a76-adb2-07701f4c7303",
            "source": {
              "x": 750,
              "y": 360
            },
            "target": {
              "cell": "edd5af30-973b-40be-b9c7-894a537276b1",
              "port": "a588080b-c81e-4b55-8afe-fca5e46af7aa"
            },
            "vertices": [
              {
                "x": 580,
                "y": 390
              }
            ]
          },
          {
            "shape": "flow",
            "attrs": {
              "line": {
                "stroke": "#333333",
                "targetMarker": {
                  "name": "block"
                },
                "sourceMarker": {
                  "name": ""
                },
                "strokeDasharray": null
              }
            },
            "width": 200,
            "height": 100,
            "zIndex": 10,
            "connector": "smooth",
            "data": {
              "type": "tm.Flow",
              "name": "Verified",
              "description": "",
              "outOfScope": false,
              "isTrustBoundary": false,
              "reasonOutOfScope": "",
              "hasOpenThreats": false,
              "isBidirectional": false,
              "isEncrypted": false,
              "isPublicNetwork": false,
              "protocol": "",
              "threats": [],
              "trustBoundaryIds": []
            },
            "labels": [
              "Verified"
            ],
            "id": "0cd61c47-7b1b-427c-bf73-7a3d8b62eb7b",
            "source": {
              "x": 400,
              "y": 160
            },
            "target": {
              "cell": "edd5af30-973b-40be-b9c7-894a537276b1",
              "port": "3eb5b585-f462-4f52-939f-818d15bb5ada"
            },
            "vertices": [
              {
                "x": 370,
                "y": 240
              }
            ]
          },
          {
            "shape": "flow",
            "attrs": {
              "line": {
                "stroke": "#333333",
                "targetMarker": {
                  "name": "block"
                },
                "sourceMarker": {
                  "name": ""
                },
                "strokeDasharray": null
              }
            },
            "width": 200,
            "height": 100,
            "zIndex": 10,
            "connector": "smooth",
            "data": {
              "type": "tm.Flow",
              "name": "Auth Verification",
              "description": "",
              "outOfScope": false,
              "isTrustBoundary": false,
              "reasonOutOfScope": "",
              "hasOpenThreats": false,
              "isBidirectional": false,
              "isEncrypted": false,
              "isPublicNetwork": false,
              "protocol": "",
              "threats": [],
              "trustBoundaryIds": []
            },
            "labels": [
              "Auth Verification"
            ],
            "id": "15c6b5d0-d674-4d01-8450-29f71e39d6d7",
            "source": {
              "x": 400,
              "y": 320
            },
            "target": {
              "cell": "525358c0-9263-4a25-82f9-9df919167926",
              "port": "4f796765-502e-4078-bee6-8dc96b106a0b"
            },
            "vertices": [
              {
                "x": 460,
                "y": 240
              }
            ]
          },
          {
            "shape": "flow",
            "attrs": {
              "line": {
                "stroke": "#333333",
                "targetMarker": {
                  "name": "block"
                },
                "sourceMarker": {
                  "name": ""
                },
                "strokeDasharray": null
              }
            },
            "width": 200,
            "height": 100,
            "zIndex": 10,
            "connector": "smooth",
            "data": {
              "type": "tm.Flow",
              "name": "Verifies the Privilege",
              "description": "",
              "outOfScope": false,
              "isTrustBoundary": false,
              "reasonOutOfScope": "",
              "hasOpenThreats": false,
              "isBidirectional": false,
              "isEncrypted": false,
              "isPublicNetwork": false,
              "protocol": "",
              "threats": [],
              "trustBoundaryIds": []
            },
            "labels": [
              "Verifies the Privilege"
            ],
            "id": "508e1f48-2855-48a3-af7e-23d45a4b113c",
            "source": {
              "x": 430,
              "y": 130
            },
            "target": {
              "cell": "b896e27f-5fca-46d8-a86a-8916279dc7c9",
              "port": "aa0c7dcd-3ec4-44ff-b7db-4326be7086be"
            },
            "vertices": [
              {
                "x": 580,
                "y": 100
              }
            ]
          },
          {
            "shape": "flow",
            "attrs": {
              "line": {
                "stroke": "#333333",
                "targetMarker": {
                  "name": "block"
                },
                "sourceMarker": {
                  "name": ""
                },
                "strokeDasharray": null
              }
            },
            "width": 200,
            "height": 100,
            "zIndex": 10,
            "connector": "smooth",
            "data": {
              "type": "tm.Flow",
              "name": "Verified",
              "description": "",
              "outOfScope": false,
              "isTrustBoundary": false,
              "reasonOutOfScope": "",
              "hasOpenThreats": false,
              "isBidirectional": false,
              "isEncrypted": false,
              "isPublicNetwork": false,
              "protocol": "",
              "threats": [],
              "trustBoundaryIds": []
            },
            "labels": [
              "Verified"
            ],
            "id": "e2c25e92-8c1d-42e0-afc6-8d3e532ce054",
            "source": {
              "x": 750,
              "y": 130
            },
            "target": {
              "cell": "525358c0-9263-4a25-82f9-9df919167926",
              "port": "a588080b-c81e-4b55-8afe-fca5e46af7aa"
            },
            "vertices": [
              {
                "x": 590,
                "y": 150
              }
            ]
          },
          {
            "shape": "flow",
            "attrs": {
              "line": {
                "stroke": "#333333",
                "targetMarker": {
                  "name": "block"
                },
                "sourceMarker": {
                  "name": ""
                },
                "strokeDasharray": null
              }
            },
            "width": 200,
            "height": 100,
            "zIndex": 10,
            "connector": "smooth",
            "data": {
              "type": "tm.Flow",
              "name": "Feedback comments saved",
              "description": "",
              "outOfScope": false,
              "isTrustBoundary": false,
              "reasonOutOfScope": "",
              "hasOpenThreats": false,
              "isBidirectional": false,
              "isEncrypted": false,
              "isPublicNetwork": false,
              "protocol": "",
              "threats": [],
              "trustBoundaryIds": []
            },
            "labels": [
              "Feedback comments saved"
            ],
            "id": "01c1c236-6b98-4605-afe8-0573615699a0",
            "source": {
              "x": 400,
              "y": 390
            },
            "target": {
              "cell": "0b6b5b7d-dae7-412a-86e4-899dae477f24",
              "port": "4f796765-502e-4078-bee6-8dc96b106a0b"
            },
            "vertices": [
              {
                "x": 200,
                "y": 410
              }
            ]
          },
          {
            "shape": "flow",
            "attrs": {
              "line": {
                "stroke": "#333333",
                "targetMarker": {
                  "name": "block"
                },
                "sourceMarker": {
                  "name": ""
                },
                "strokeDasharray": null
              }
            },
            "width": 200,
            "height": 100,
            "zIndex": 10,
            "connector": "smooth",
            "data": {
              "type": "tm.Flow",
              "name": "Insert Feedback Comments",
              "description": "",
              "outOfScope": false,
              "isTrustBoundary": false,
              "reasonOutOfScope": "",
              "hasOpenThreats": false,
              "isBidirectional": false,
              "isEncrypted": false,
              "isPublicNetwork": false,
              "protocol": "",
              "threats": [],
              "trustBoundaryIds": []
            },
            "labels": [
              "Insert Feedback Comments"
            ],
            "id": "e265327f-1bbf-4b41-862f-9e7e45ee19e4",
            "source": {
              "x": 70,
              "y": 368
            },
            "target": {
              "cell": "edd5af30-973b-40be-b9c7-894a537276b1",
              "port": "aa0c7dcd-3ec4-44ff-b7db-4326be7086be"
            },
            "vertices": [
              {
                "x": 230,
                "y": 368
              }
            ]
          },
          {
            "position": {
              "x": 10,
              "y": 327
            },
            "size": {
              "width": 60,
              "height": 60
            },
            "attrs": {
              "body": {
                "stroke": "#333333",
                "strokeWidth": 1.5,
                "strokeDasharray": null
              }
            },
            "visible": true,
            "shape": "process",
            "ports": {
              "groups": {
                "top": {
                  "position": "top",
                  "attrs": {
                    "circle": {
                      "r": 4,
                      "magnet": true,
                      "stroke": "#5F95FF",
                      "strokeWidth": 1,
                      "fill": "#fff",
                      "style": {
                        "visibility": "hidden"
                      }
                    }
                  }
                },
                "right": {
                  "position": "right",
                  "attrs": {
                    "circle": {
                      "r": 4,
                      "magnet": true,
                      "stroke": "#5F95FF",
                      "strokeWidth": 1,
                      "fill": "#fff",
                      "style": {
                        "visibility": "hidden"
                      }
                    }
                  }
                },
                "bottom": {
                  "position": "bottom",
                  "attrs": {
                    "circle": {
                      "r": 4,
                      "magnet": true,
                      "stroke": "#5F95FF",
                      "strokeWidth": 1,
                      "fill": "#fff",
                      "style": {
                        "visibility": "hidden"
                      }
                    }
                  }
                },
                "left": {
                  "position": "left",
                  "attrs": {
                    "circle": {
                      "r": 4,
                      "magnet": true,
                      "stroke": "#5F95FF",
                      "strokeWidth": 1,
                      "fill": "#fff",
                      "style": {
                        "visibility": "hidden"
                      }
                    }
                  }
                }
              },
              "items": [
                {
                  "group": "top",
                  "id": "3eb5b585-f462-4f52-939f-818d15bb5ada"
                },
                {
                  "group": "right",
                  "id": "a588080b-c81e-4b55-8afe-fca5e46af7aa"
                },
                {
                  "group": "bottom",
                  "id": "4f796765-502e-4078-bee6-8dc96b106a0b"
                },
                {
                  "group": "left",
                  "id": "aa0c7dcd-3ec4-44ff-b7db-4326be7086be"
                }
              ]
            },
            "id": "0b6b5b7d-dae7-412a-86e4-899dae477f24",
            "zIndex": 11,
            "data": {
              "type": "tm.Process",
              "name": "Process",
              "description": "",
              "outOfScope": false,
              "isTrustBoundary": false,
              "reasonOutOfScope": "",
              "hasOpenThreats": false,
              "handlesCardPayment": false,
              "handlesGoodsOrServices": false,
              "isWebApplication": false,
              "privilegeLevel": "",
              "threats": []
            }
          },
          {
            "shape": "trust-boundary-curve",
            "width": 200,
            "height": 100,
            "zIndex": 12,
            "connector": "smooth",
            "data": {
              "type": "tm.Boundary",
              "name": "Trust Boundary",
              "description": "",
              "isTrustBoundary": true,
              "hasOpenThreats": false,
              "crossingFlows": [],
              "containedElements": []
            },
            "labels": [
              "Trust Boundary"
            ],
            "id": "1549ff8c-0726-4438-8385-f0654eddce6b",
            "source": {
              "x": 129,
              "y": 160
            },
            "target": {
              "x": 590,
              "y": 170
            },
            "vertices": [
              {
                "x": 390,
                "y": 200
              }
            ]
          },
          {
            "shape": "flow",
            "attrs": {
              "line": {
                "stroke": "#333333",
                "targetMarker": {
                  "name": "block"
                },
                "sourceMarker": {
                  "name": ""
                },
                "strokeDasharray": null
              }
            },
            "width": 200,
            "height": 100,
            "zIndex": 13,
            "connector": "smooth",
            "data": {
              "type": "tm.Flow",
              "name": "Data Flow",
              "description": "",
              "outOfScope": false,
              "isTrustBoundary": false,
              "reasonOutOfScope": "",
              "hasOpenThreats": false,
              "isBidirectional": false,
              "isEncrypted": false,
              "isPublicNetwork": false,
              "protocol": "",
              "threats": [],
              "trustBoundaryIds": []
            },
            "labels": [
              "Data Flow"
            ],
            "id": "4b23a4b9-75ce-42c6-8341-a9d12f85c8bb",
            "source": {
              "x": 400,
              "y": 330
            },
            "target": {
              "cell": "0b6b5b7d-dae7-412a-86e4-899dae477f24",
              "port": "3eb5b585-f462-4f52-939f-818d15bb5ada"
            },
            "vertices": []
          },
          {
            "position": {
              "x": 160,
              "y": 280
            },
            "size": {
              "width": 112.5,
              "height": 60
            },
            "visible": true,
            "shape": "td-text-block",
            "id": "bb326ed3-81e7-4fcc-a8c4-f03edf77556b",
            "zIndex": 14,
            "data": {
              "type": "tm.Text",
              "name": "Descriptive text",
              "hasOpenThreats": false
            },
            "tools": {
              "items": [
                "boundary",
                "button-remove"
              ],
              "name": null
            }
          }
        ]
      }
    ],
    "diagramTop": 2,
    "reviewer": "",
    "threatTop": 0
  }
}